README.md
setup.cfg
setup.py
parity/__init__.py
parity/counterfactual_explainer.py
parity/deep_explainer.py
parity/explainer.py
parity/fair.py
parity/fairness_metrics.py
parity/pair.py
parity/reduction.py
parity/thresholdOptimizer.py
parity/transfer.py
parity_fairness.egg-info/PKG-INFO
parity_fairness.egg-info/SOURCES.txt
parity_fairness.egg-info/dependency_links.txt
parity_fairness.egg-info/requires.txt
parity_fairness.egg-info/top_level.txt