Metadata-Version: 2.1
Name: parity-fairness
Version: 0.1.29
Summary: Measure bias from data and machine learning models.
Home-page: https://github.com/xmpuspus/parity-fairness
Author: Xavier M. Puspus
Author-email: xpuspus@gmail.com
License: MIT
Download-URL: https://github.com/xmpuspus/parity-fairness/archive/v_01.29.tar.gz
Keywords: fairness,bias,explainability,AI,machine learning,data
Platform: UNKNOWN
Classifier: Development Status :: 3 - Alpha
Classifier: Intended Audience :: Developers
Classifier: Topic :: Software Development :: Build Tools
Classifier: License :: OSI Approved :: MIT License
Classifier: Programming Language :: Python :: 3
Classifier: Programming Language :: Python :: 3.4
Classifier: Programming Language :: Python :: 3.5
Classifier: Programming Language :: Python :: 3.6
Classifier: Programming Language :: Python :: 3.7
